Metadata-Version: 1.1
Name: pyseeyou
Version: 1.0.2
Summary: A Python Parser for the ICU MessageFormat.
Home-page: https://github.com/rolepoint/pyseeyou
Author: Siame Rafiq
Author-email: mail@sia.me.uk
License: UNKNOWN
Download-URL: https://github.com/rolepoint/pyseeyou/archive/v1.0.2.tar.gz
Keywords: python i18n messageformat python3 python2
Platform: UNKNOWN
